setup.py
ddlc/__init__.py
ddlc/client.py
ddlc/core.py
ddlc/parse.py
ddlc/util.py
ddlc.egg-info/PKG-INFO
ddlc.egg-info/SOURCES.txt
ddlc.egg-info/dependency_links.txt
ddlc.egg-info/top_level.txt