Metadata-Version: 1.1
Name: ddlc
Version: 0.0.1a0
Summary: Framework for parsing complex line commands.
Home-page: http://just-monika.club/ddlc
Author: Kira Evans
Author-email: contact@kne42.me
License: Modified BSD
Download-URL: https://github.com/just-monika/ddlc
Platform: UNKNOWN
